project_FPGA.srcs/sources_1/new/packetizer_fsm.v
module packetizer_fsm (
    input wire clk,
    input wire rst,                   // Active-high synchronous reset
    input wire fifo_empty,
    input wire tx_ready,
    input wire [7:0] fifo_data_out,
    output reg fifo_rd_en,
    output reg serial_out,
    output reg tx_busy
);

    // FSM state encoding
    parameter IDLE      = 2'b00;
    parameter READ      = 2'b01;
    parameter SEND      = 2'b10;
    parameter WAIT_DONE = 2'b11;

    reg [1:0] state, next_state;

    // Internal signals
    reg [9:0] shift_reg;     // 1 start bit + 8 data bits + 1 stop bit
    reg [3:0] bit_count;     // up to 10 bits

    // FSM: Sequential block
    always @(posedge clk) begin
        if (rst) begin
            state <= IDLE;
        end else begin
            state <= next_state;
        end
    end

    // FSM: Combinational block for state transitions
    always @(*) begin
        next_state = state;
        case (state)
            IDLE: begin
                if (!fifo_empty && tx_ready)
                    next_state = READ;
            end

            READ: begin
                next_state = SEND;
            end

            SEND: begin
                if (bit_count == 4'd9)
                    next_state = WAIT_DONE;
            end

            WAIT_DONE: begin
                if (tx_ready)
                    next_state = IDLE;
            end

            default: next_state = IDLE;
        endcase
    end

    // Output and data path logic
    always @(posedge clk) begin
        if (rst) begin
            fifo_rd_en  <= 0;
            serial_out  <= 1'b1; // idle state of UART line is high
            tx_busy     <= 0;
            shift_reg   <= 10'b1111111111;
            bit_count   <= 0;
        end else begin
            case (state)
                IDLE: begin
                    fifo_rd_en  <= 0;
                    serial_out  <= 1'b1;
                    tx_busy     <= 0;
                    bit_count   <= 0;
                end

                READ: begin
                    fifo_rd_en  <= 1;  // trigger FIFO read
                    tx_busy     <= 1;
                    // Load 10-bit shift register: start(0) + data[7:0] + stop(1)
                    shift_reg   <= {1'b1, fifo_data_out, 1'b0};
                end

                SEND: begin
                    fifo_rd_en <= 0;
                    serial_out <= shift_reg[0];
                    shift_reg  <= {1'b1, shift_reg[9:1]}; // shift right, pad stop bit
                    bit_count  <= bit_count + 1;
                end

                WAIT_DONE: begin
                    serial_out <= 1'b1; // line idle
                end

                default: begin
                    fifo_rd_en <= 0;
                    serial_out <= 1'b1;
                    tx_busy    <= 0;
                end
            endcase
        end
    end

endmodule

project_FPGA.srcs/sources_1/new/fifo.v
module fifo (
    input wire clk,
    input wire rst,
    input wire wr_en,
    input wire rd_en,
    input wire [7:0] data_in,
    output reg [7:0] data_out,
    output reg fifo_full,
    output reg fifo_empty,
    output reg data_out_valid
);

    parameter DEPTH = 16;
    parameter ADDR_WIDTH = 4; // log2(16) = 4

    reg [7:0] mem [0:DEPTH-1];
    reg [ADDR_WIDTH-1:0] wr_ptr, rd_ptr;
    reg [ADDR_WIDTH:0] count; // count range = 0 to DEPTH

    always @(posedge clk) begin
        if (rst) begin
            wr_ptr <= 0;
            rd_ptr <= 0;
            count  <= 0;
            fifo_full <= 0;
            fifo_empty <= 1;
            data_out_valid <= 0;
        end else begin
            // Write operation
            if (wr_en && !fifo_full) begin
                mem[wr_ptr] <= data_in;
                wr_ptr <= wr_ptr + 1;
                count <= count + 1;
            end

            // Read operation
            if (rd_en && !fifo_empty) begin
                data_out <= mem[rd_ptr];
                rd_ptr <= rd_ptr + 1;
                count <= count - 1;
                data_out_valid <= 1;
            end else begin
                data_out_valid <= 0;
            end

            // Status
            fifo_full <= (count == DEPTH);
            fifo_empty <= (count == 0);
        end
    end

endmodule

project_FPGA.srcs/sources_1/new/uart_packetizer_top.v
module uart_packetizer_top (
    input wire clk,
    input wire rst,
    input wire [7:0] data_in,
    input wire data_valid,
    input wire tx_ready,
    output wire serial_out,
    output wire fifo_full,
    output wire tx_busy
);

    wire [7:0] fifo_data_out;
    wire fifo_empty, fifo_rd_en, data_out_valid;

    // FIFO instance
    fifo u_fifo (
        .clk(clk),
        .rst(rst),
        .wr_en(data_valid && !fifo_full),
        .rd_en(fifo_rd_en),
        .data_in(data_in),
        .data_out(fifo_data_out),
        .fifo_full(fifo_full),
        .fifo_empty(fifo_empty),
        .data_out_valid(data_out_valid)
    );

    // FSM instance
    packetizer_fsm u_fsm (
        .clk(clk),
        .rst(rst),
        .fifo_empty(fifo_empty),
        .tx_ready(tx_ready),
        .fifo_data_out(fifo_data_out),
        .fifo_rd_en(fifo_rd_en),
        .serial_out(serial_out),
        .tx_busy(tx_busy)
    );

endmodule

project_FPGA.srcs/sim_1/new/uart_packetizer_tb.v
`timescale 1ns/1ps

module uart_packetizer_tb;

    reg clk = 0;
    reg rst = 1;
    reg tx_ready = 1;
    reg data_valid = 0;
    reg [7:0] data_in;

    wire serial_out;
    wire fifo_full, tx_busy;

    uart_packetizer_top uut (
        .clk(clk),
        .rst(rst),
        .data_in(data_in),
        .data_valid(data_valid),
        .tx_ready(tx_ready),
        .serial_out(serial_out),
        .fifo_full(fifo_full),
        .tx_busy(tx_busy)
    );

    // Clock generation: 50MHz
    always #10 clk = ~clk;

    initial begin
        $dumpfile("uart_packetizer.vcd");
        $dumpvars(0, uart_packetizer_tb);

        #30 rst = 0;

        // Write two data bytes into FIFO
        #20 send_byte(8'hAB);
        #200 send_byte(8'h3C);

        // Wait for transmission to complete
        #2000 $finish;
    end

    task send_byte(input [7:0] byte);
        begin
            data_in = byte;
            data_valid = 1;
            #20;
            data_valid = 0;
        end
    endtask

endmodule

project_FPGA/project_FPGA.sim/sim_1/behav/xsim/uart_packetizer.vcd
$date
   Mon Jun  2 01:42:55 2025
$end
$version
  2023.1
$end
$timescale
  1ps
$end
$scope module uart_packetizer_tb $end
$var reg 1 ! clk $end
$var reg 1 " rst $end
$var reg 1 # tx_ready $end
$var reg 1 $ data_valid $end
$var reg 8 % data_in [7:0] $end
$var wire 1 & serial_out $end
$var wire 1 ' fifo_full $end
$var wire 1 ( tx_busy $end
$scope module uut $end
$var wire 1 ) clk $end
$var wire 1 * rst $end
$var wire 8 + data_in [7:0] $end
$var wire 1 , data_valid $end
$var wire 1 - tx_ready $end
$var wire 1 & serial_out $end
$var wire 1 ' fifo_full $end
$var wire 1 ( tx_busy $end
$var wire 8 . fifo_data_out [7:0] $end
$var wire 1 / fifo_empty $end
$var wire 1 0 fifo_rd_en $end
$var wire 1 1 data_out_valid $end
$scope module u_fifo $end
$var wire 1 ) clk $end
$var wire 1 * rst $end
$var wire 1 2 wr_en $end
$var wire 1 0 rd_en $end
$var wire 8 + data_in [7:0] $end
$var reg 8 3 data_out [7:0] $end
$var reg 1 4 fifo_full $end
$var reg 1 5 fifo_empty $end
$var reg 1 6 data_out_valid $end
$var reg 4 7 wr_ptr [3:0] $end
$var reg 4 8 rd_ptr [3:0] $end
$var reg 5 9 count [4:0] $end
$upscope $end
$scope module u_fsm $end
$var wire 1 ) clk $end
$var wire 1 * rst $end
$var wire 1 / fifo_empty $end
$var wire 1 - tx_ready $end
$var wire 8 . fifo_data_out [7:0] $end
$var reg 1 : fifo_rd_en $end
$var reg 1 ; serial_out $end
$var reg 1 < tx_busy $end
$var reg 2 = state [1:0] $end
$var reg 2 > next_state [1:0] $end
$var reg 10 ? shift_reg [9:0] $end
$var reg 4 @ bit_count [3:0] $end
$upscope $end
$upscope $end
$scope task send_byte $end
$var reg 8 A byte [7:0] $end
$upscope $end
$upscope $end
$enddefinitions $end
#0
$dumpvars
0!
1"
1#
0$
bx %
x&
x'
x(
0)
1*
bx +
0,
1-
bx .
x/
x0
x1
02
bx 3
x4
x5
x6
bx 7
bx 8
bx 9
x:
x;
x<
bx =
b0 >
bx ?
bx @
bx A
$end
#10000
1!
1&
0'
0(
1)
1/
00
01
04
15
06
b0 7
b0 8
b0 9
0:
1;
0<
b0 =
b1111111111 ?
b0 @
#20000
0!
0)
#30000
1!
0"
1)
0*
#40000
0!
0)
#50000
1!
1$
b10101011 %
1)
b10101011 +
1,
12
b1 7
b1 9
b10101011 A
#60000
0!
0)
#70000
1!
0$
1)
0,
0/
02
05
b1 >
#80000
0!
0)
#90000
1!
1)
b1 =
b10 >
#100000
0!
0)
#110000
1!
1(
1)
10
1:
1<
b10 =
b1xxxxxxxx0 ?
#120000
0!
0)
#130000
1!
0&
1)
b10101011 .
00
11
b10101011 3
16
b1 8
b0 9
0:
0;
b11xxxxxxxx ?
b1 @
#140000
0!
0)
#150000
1!
x&
1)
1/
01
15
06
x;
b111xxxxxxx ?
b10 @
#160000
0!
0)
#170000
1!
1)
b1111xxxxxx ?
b11 @
#180000
0!
0)
#190000
1!
1)
b11111xxxxx ?
b100 @
#200000
0!
0)
#210000
1!
1)
b111111xxxx ?
b101 @
#220000
0!
0)
#230000
1!
1)
b1111111xxx ?
b110 @
#240000
0!
0)
#250000
1!
1)
b11111111xx ?
b111 @
#260000
0!
0)
#270000
1!
1$
b111100 %
1)
b111100 +
1,
12
b10 7
b1 9
b111111111x ?
b1000 @
b111100 A
#280000
0!
0)
#290000
1!
0$
1)
0,
0/
02
05
b11 >
b1111111111 ?
b1001 @
#300000
0!
0)
#310000
1!
1&
1)
1;
b11 =
b0 >
b1010 @
#320000
0!
0)
#330000
1!
1)
b0 =
b1 >
#340000
0!
0)
#350000
1!
0(
1)
0<
b1 =
b10 >
b0 @
#360000
0!
0)
#370000
1!
1(
1)
10
1:
1<
b10 =
b1101010110 ?
#380000
0!
0)
#390000
1!
0&
1)
b111100 .
00
11
b111100 3
16
b10 8
b0 9
0:
0;
b1110101011 ?
b1 @
#400000
0!
0)
#410000
1!
1&
1)
1/
01
15
06
1;
b1111010101 ?
b10 @
#420000
0!
0)
#430000
1!
1)
b1111101010 ?
b11 @
#440000
0!
0)
#450000
1!
0&
1)
0;
b1111110101 ?
b100 @
#460000
0!
0)
#470000
1!
1&
1)
1;
b1111111010 ?
b101 @
#480000
0!
0)
#490000
1!
0&
1)
0;
b1111111101 ?
b110 @
#500000
0!
0)
#510000
1!
1&
1)
1;
b1111111110 ?
b111 @
#520000
0!
0)
#530000
1!
0&
1)
0;
b1111111111 ?
b1000 @
#540000
0!
0)
#550000
1!
1&
1)
1;
b11 >
b1001 @
#560000
0!
0)
#570000
1!
1)
b11 =
b0 >
b1010 @
#580000
0!
0)
#590000
1!
1)
b0 =
#600000
0!
0)
#610000
1!
0(
1)
0<
b0 @
